{ "deck_data": "{ \"background_color\": 671752.0, \"on\": true, \"grid_y\": 10.0, \"snap_grid\": true, \"lb_version\": \"2022.5.1\", \"background_image\": \"\", \"sammi_version\": \"2022.5.1\", \"encrypted\": false, \"adaptive_resizing\": true, \"unique_id\": \"20221110062830968484619\", \"button_list\": [ { \"color\": 12632256.0, \"persistent\": 1.0, \"text\": \"!stop\", \"release_duration\": 0.0, \"queueable\": 0.0, \"command_list\": [ { \"cmd\": 6.0, \"obsid\": \"Main\", \"pos\": 0.0, \"vis\": 1.0, \"ms\": 0.0, \"sel\": 0.0, \"dis\": 0.0, \"xpan\": 0.0, \"b0\": \"Stops all buttons in case of emergency\", \"v0\": 0.0 }, { \"cmd\": 133.0, \"v1\": 1.0, \"obsid\": \"Main\", \"pos\": 1.0, \"vis\": 1.0, \"ms\": 0.0, \"sel\": 0.0, \"dis\": 0.0, \"xpan\": 0.0, \"b0\": \"all\", \"v0\": 1.0, \"v2\": 0.0 }, { \"b1\": \"\\\/$kbmChannelName$\\\/\", \"cmd\": 148.0, \"obsid\": \"Main\", \"pos\": 2.0, \"vis\": 1.0, \"ms\": 0.0, \"sel\": 0.0, \"dis\": 0.0, \"xpan\": 0.0, \"b0\": \"SAMMI: Interrupting all ongoing buttons...\" } ], \"press_type\": 0.0, \"x\": 0.0, \"border\": 2.0, \"image\": \"\", \"triggers\": [ { \"sub\": 0.0, \"case_sensitive\": 0.0, \"founder\": 0.0, \"message\": \"!stop\", \"moderator\": 1.0, \"group_id\": \"\", \"vip\": 0.0, \"button_id\": \"ID94\", \"broadcaster\": 0.0, \"trg\": 0.0, \"allow_empty_wildcard\": 0.0 }, { \"sub\": 0.0, \"case_sensitive\": 0.0, \"founder\": 0.0, \"message\": \"!pause\", \"moderator\": 1.0, \"group_id\": \"\", \"vip\": 0.0, \"button_id\": \"ID94\", \"broadcaster\": 0.0, \"trg\": 0.0, \"allow_empty_wildcard\": 0.0 } ], \"group_id\": \"\", \"overlappable\": 0.0, \"init_variable\": \"\", \"deck\": 1.0, \"width\": 0.10000000000000000555111512312578, \"button_id\": \"ID94\", \"button_duration\": 0.0, \"y\": 0.0, \"switch_deck\": \"\", \"height\": 0.10000000000000000555111512312578, \"release_list\": [ ], \"functions\": 81.0, \"stretch\": 0.0 }, { \"color\": 12632256.0, \"persistent\": 1.0, \"text\": \"!assignChannel\", \"release_duration\": 0.0, \"queueable\": 0.0, \"command_list\": [ { \"cmd\": 6.0, \"obsid\": \"Main\", \"pos\": 0.0, \"vis\": 1.0, \"ms\": 0.0, \"sel\": 0.0, \"dis\": 0.0, \"xpan\": 0.0, \"b0\": \"saves the setting which channel to output chat messages to\", \"v0\": 0.0 }, { \"b1\": \"message\", \"cmd\": 66.0, \"obsid\": \"Main\", \"pos\": 1.0, \"vis\": 1.0, \"ms\": 0.0, \"sel\": 0.0, \"dis\": 0.0, \"xpan\": 0.0, \"b0\": \"kbmAssignMessage\" }, { \"b1\": \"\\\/$kbmAssignMessage$\\\/\", \"cmd\": 92.0, \"obsid\": \"Main\", \"pos\": 2.0, \"vis\": 1.0, \"ms\": 0.0, \"sel\": 0.0, \"dis\": 0.0, \"xpan\": 0.0, \"b0\": \"kbmMessageHasAdd\", \"b2\": \"@\", \"v0\": 0.0 }, { \"b53\": \"\", \"b5\": \"\", \"b13\": \"==\", \"v14\": 0.0, \"b36\": \"\", \"b38\": \"\", \"v10\": 0.0, \"b32\": \"\", \"b19\": \"==\", \"b57\": \"\", \"b59\": \"\", \"b17\": \"\", \"b1\": \"==\", \"v18\": 0.0, \"v16\": 0.0, \"b34\": \"==\", \"b7\": \"==\", \"b11\": \"\", \"b9\": \"\", \"b51\": \"\", \"b15\": \"\", \"b3\": \"\", \"b55\": \"==\", \"v12\": 0.0, \"cmd\": 7.0, \"b30\": \"\", \"b43\": \"==\", \"v21\": 0.0, \"v1\": 1.0, \"b26\": \"\", \"b28\": \"==\", \"obsid\": \"Main\", \"b22\": \"==\", \"pos\": 3.0, \"v5\": 0.0, \"b47\": \"\", \"b49\": \"==\", \"v3\": 0.0, \"vis\": 1.0, \"b24\": \"\", \"ms\": 0.0, \"b41\": \"\", \"sel\": 0.0, \"b45\": \"\", \"v9\": 0.0, \"dis\": 0.0, \"xpan\": 0.0, \"b20\": \"\", \"v7\": 0.0, \"b33\": \"\", \"v11\": 0.0, \"b16\": \"==\", \"b0\": \"kbmMessageHasAdd\", \"b58\": \"==\", \"b56\": \"\", \"b18\": \"\", \"b4\": \"==\", \"b12\": \"\", \"b52\": \"==\", \"b39\": \"\", \"b37\": \"==\", \"v15\": 0.0, \"b54\": \"\", \"b14\": \"\", \"b2\": \"0\", \"b31\": \"==\", \"v13\": 0.0, \"b35\": \"\", \"v17\": 0.0, \"v19\": 0.0, \"b50\": \"\", \"b8\": \"\", \"b6\": \"\", \"b10\": \"==\", \"b23\": \"\", \"v4\": 0.0, \"b48\": \"\", \"b46\": \"==\", \"v20\": 0.0, \"b42\": \"\", \"b29\": \"\", \"v0\": 1.0, \"b27\": \"\", \"b44\": \"\", \"b21\": \"\", \"v6\": 0.0, \"v8\": 0.0, \"v2\": 1.0, \"b25\": \"==\", \"b40\": \"==\", \"v22\": 0.0 }, { \"b1\": \"\\\/$kbmAssignMessage$\\\/\", \"b3\": \"15\", \"cmd\": 94.0, \"obsid\": \"Main\", \"pos\": 4.0, \"vis\": 1.0, \"ms\": 0.0, \"sel\": 0.0, \"dis\": 0.0, \"xpan\": 0.0, \"b0\": \"kbmChannelNameFormatted\", \"b2\": \"1\" }, { \"b1\": \"\\\/$kbmAssignMessage$\\\/\", \"b3\": \"16\", \"cmd\": 94.0, \"obsid\": \"Main\", \"pos\": 5.0, \"vis\": 1.0, \"ms\": 0.0, \"sel\": 0.0, \"dis\": 0.0, \"xpan\": 0.0, \"b0\": \"kbmChannelNameFormatted\", \"b2\": \"1\" }, { \"b1\": \"\\\/$kbmChannelNameFormatted$\\\/\", \"cmd\": 90.0, \"obsid\": \"Main\", \"pos\": 6.0, \"vis\": 1.0, \"ms\": 0.0, \"sel\": 0.0, \"dis\": 0.0, \"xpan\": 0.0, \"b0\": \"kbmChannelNameExport\" }, { \"b1\": \"core\", \"b3\": \"\\\/$kbmChannelNameExport$\\\/\", \"cmd\": 126.0, \"obsid\": \"Main\", \"pos\": 7.0, \"vis\": 1.0, \"ms\": 0.0, \"sel\": 0.0, \"dis\": 0.0, \"xpan\": 0.0, \"b0\": \"kbmSettings.ini\", \"b2\": \"channelName\" }, { \"b1\": \"\\\/$kbmChannelNameExport$\\\/\", \"cmd\": 148.0, \"obsid\": \"Main\", \"pos\": 8.0, \"vis\": 1.0, \"ms\": 0.0, \"sel\": 0.0, \"dis\": 0.0, \"xpan\": 0.0, \"b0\": \"SAMMI: message output set to channel: \\\/$kbmChannelNameExport$\\\/\" } ], \"press_type\": 0.0, \"x\": 0.0, \"border\": 2.0, \"image\": \"\", \"triggers\": [ { \"sub\": 0.0, \"case_sensitive\": 0.0, \"founder\": 0.0, \"message\": \"!assignchannel *\", \"moderator\": 0.0, \"group_id\": \"\", \"vip\": 0.0, \"button_id\": \"kbmAssignChannel\", \"broadcaster\": 1.0, \"trg\": 0.0, \"allow_empty_wildcard\": 0.0 } ], \"group_id\": \"\", \"overlappable\": 0.0, \"init_variable\": \"\", \"deck\": 1.0, \"width\": 0.10000000000000000555111512312578, \"button_id\": \"kbmAssignChannel\", \"button_duration\": 0.0, \"y\": 0.10000000000000000555111512312578, \"switch_deck\": \"\", \"height\": 0.10000000000000000555111512312578, \"release_list\": [ ], \"functions\": 81.0, \"stretch\": 0.0 }, { \"color\": 12632256.0, \"persistent\": 1.0, \"text\": \"!kbmhelp\", \"release_duration\": 0.0, \"queueable\": 0.0, \"command_list\": [ { \"cmd\": 6.0, \"obsid\": \"Main\", \"pos\": 0.0, \"vis\": 1.0, \"ms\": 0.0, \"sel\": 0.0, \"dis\": 0.0, \"xpan\": 0.0, \"b0\": \"help command for this deck\", \"v0\": 0.0 }, { \"cmd\": 6.0, \"obsid\": \"Main\", \"pos\": 1.0, \"vis\": 1.0, \"ms\": 0.0, \"sel\": 0.0, \"dis\": 0.0, \"xpan\": 0.0, \"b0\": \"pulls settings from ini for channel output and use of prefix\", \"v0\": 0.0 }, { \"b1\": \"core\", \"b3\": \"kbmChannelName\", \"cmd\": 127.0, \"obsid\": \"Main\", \"pos\": 2.0, \"vis\": 1.0, \"ms\": 0.0, \"sel\": 0.0, \"dis\": 0.0, \"xpan\": 0.0, \"b0\": \"kbmSettings.ini\", \"b2\": \"channelName\" }, { \"b1\": \"core\", \"b3\": \"kbmPrefix\", \"cmd\": 127.0, \"obsid\": \"Main\", \"pos\": 3.0, \"vis\": 1.0, \"ms\": 0.0, \"sel\": 0.0, \"dis\": 0.0, \"xpan\": 0.0, \"b0\": \"kbmSettings.ini\", \"b2\": \"prefix\" }, { \"cmd\": 6.0, \"obsid\": \"Main\", \"pos\": 4.0, \"vis\": 1.0, \"ms\": 0.0, \"sel\": 0.0, \"dis\": 0.0, \"xpan\": 0.0, \"b0\": \"help message below\", \"v0\": 0.0 }, { \"b1\": \"\\\/$kbmChannelName$\\\/\", \"cmd\": 148.0, \"obsid\": \"Main\", \"pos\": 5.0, \"vis\": 1.0, \"ms\": 0.0, \"sel\": 0.0, \"dis\": 0.0, \"xpan\": 0.0, \"b0\": \"\\\/$kbmPrefix$\\\/ --To see the help for a module use \\\"!kbmhelp <module name>\\\" example \\\"!kbmhelp autoso\\\" to get the help for autoso. -- use \\\"!stop\\\" to stop ALL sammi buttons. -- To change the channel Sammi outputs its messages on use \\\"!setchannelname username\\\". -- to turn the \\\"keyBOTmedic: \\\" prefix on\\\/off in chat use \\\"!prefix <on or off>\\\". -- To display the current version of all kbm modules use \\\"!kbmversion\\\". -- To display Medics message about sharing keyBOTmedic use \\\"!keybotmedic\\\". -- END\" } ], \"press_type\": 0.0, \"x\": 0.10000000000000000555111512312578, \"border\": 2.0, \"image\": \"\", \"triggers\": [ { \"sub\": 0.0, \"user_name\": \"\", \"case_sensitive\": 0.0, \"founder\": 0.0, \"message\": \"!kbmhelp\", \"moderator\": 1.0, \"group_id\": \"\", \"vip\": 0.0, \"button_id\": \"helpKbm\", \"broadcaster\": 0.0, \"trg\": 0.0, \"allow_empty_wildcard\": 0.0 }, { \"sub\": 0.0, \"user_name\": \"\", \"case_sensitive\": 0.0, \"founder\": 0.0, \"message\": \"!help\", \"moderator\": 1.0, \"group_id\": \"\", \"vip\": 0.0, \"button_id\": \"helpKbm\", \"broadcaster\": 0.0, \"trg\": 0.0, \"allow_empty_wildcard\": 0.0 } ], \"group_id\": \"\", \"overlappable\": 0.0, \"init_variable\": \"\", \"deck\": 1.0, \"width\": 0.10000000000000000555111512312578, \"button_id\": \"helpKbm\", \"button_duration\": 0.0, \"y\": 0.0, \"switch_deck\": \"\", \"height\": 0.10000000000000000555111512312578, \"release_list\": [ ], \"functions\": 81.0, \"stretch\": 0.0 }, { \"color\": 12632256.0, \"persistent\": 1.0, \"text\": \"!bot\", \"release_duration\": 0.0, \"queueable\": 0.0, \"command_list\": [ { \"cmd\": 6.0, \"obsid\": \"Main\", \"pos\": 0.0, \"vis\": 1.0, \"ms\": 0.0, \"sel\": 0.0, \"dis\": 0.0, \"xpan\": 0.0, \"b0\": \"check if alive message for bot\", \"v0\": 0.0 }, { \"b1\": \"core\", \"b3\": \"kbmChannelName\", \"cmd\": 127.0, \"obsid\": \"Main\", \"pos\": 1.0, \"vis\": 1.0, \"ms\": 0.0, \"sel\": 0.0, \"dis\": 0.0, \"xpan\": 0.0, \"b0\": \"kbmSettings.ini\", \"b2\": \"channelName\" }, { \"b1\": \"\\\/$kbmChannelName$\\\/\", \"cmd\": 148.0, \"obsid\": \"Main\", \"pos\": 2.0, \"vis\": 1.0, \"ms\": 0.0, \"sel\": 0.0, \"dis\": 0.0, \"xpan\": 0.0, \"b0\": \"keyBOTmedic: Reporting for duty! if you need help type !kbmhelp\" } ], \"press_type\": 0.0, \"x\": 0.10000000000000000555111512312578, \"border\": 2.0, \"image\": \"\", \"triggers\": [ { \"sub\": 0.0, \"case_sensitive\": 0.0, \"founder\": 0.0, \"message\": \"!bot\", \"moderator\": 1.0, \"group_id\": \"\", \"vip\": 0.0, \"button_id\": \"ID3\", \"broadcaster\": 0.0, \"trg\": 0.0, \"allow_empty_wildcard\": 0.0 } ], \"group_id\": \"\", \"overlappable\": 0.0, \"init_variable\": \"\", \"deck\": 1.0, \"width\": 0.10000000000000000555111512312578, \"button_id\": \"ID3\", \"button_duration\": 0.0, \"y\": 0.10000000000000000555111512312578, \"switch_deck\": \"\", \"height\": 0.10000000000000000555111512312578, \"release_list\": [ ], \"functions\": 81.0, \"stretch\": 0.0 }, { \"color\": 12632256.0, \"persistent\": 1.0, \"text\": \"!prefix\", \"release_duration\": 0.0, \"queueable\": 0.0, \"command_list\": [ { \"cmd\": 6.0, \"obsid\": \"Main\", \"pos\": 0.0, \"vis\": 1.0, \"ms\": 0.0, \"sel\": false, \"dis\": 0.0, \"xpan\": 0.0, \"b0\": \"pulls settings from ini for chat channel output and use of prefix\", \"v0\": 0.0 }, { \"b1\": \"core\", \"b3\": \"kbmChannelName\", \"cmd\": 127.0, \"obsid\": \"Main\", \"pos\": 1.0, \"vis\": 1.0, \"ms\": 0.0, \"sel\": false, \"dis\": 0.0, \"xpan\": 0.0, \"b0\": \"kbmSettings.ini\", \"b2\": \"channelName\" }, { \"b1\": \"core\", \"b3\": \"kbmPrefix\", \"cmd\": 127.0, \"obsid\": \"Main\", \"pos\": 2.0, \"vis\": 1.0, \"ms\": 0.0, \"sel\": false, \"dis\": 0.0, \"xpan\": 0.0, \"b0\": \"kbmSettings.ini\", \"b2\": \"prefix\" }, { \"cmd\": 6.0, \"obsid\": \"Main\", \"pos\": 3.0, \"vis\": 1.0, \"ms\": 0.0, \"sel\": false, \"dis\": 0.0, \"xpan\": 0.0, \"b0\": \"Allows switching between use of the Sammi: prefix before chat messages and saves it to ini\", \"v0\": 0.0 }, { \"b1\": \"message\", \"cmd\": 66.0, \"obsid\": \"Main\", \"pos\": 4.0, \"vis\": 1.0, \"ms\": 0.0, \"sel\": false, \"dis\": 0.0, \"xpan\": 0.0, \"b0\": \"kbmPrefixMessage\" }, { \"b1\": \"\\\/$kbmPrefixMessage$\\\/\", \"b3\": \"8\", \"cmd\": 94.0, \"obsid\": \"Main\", \"pos\": 5.0, \"vis\": 1.0, \"ms\": 0.0, \"sel\": false, \"dis\": 0.0, \"xpan\": 0.0, \"b0\": \"kbmPrefixFormatted\", \"b2\": \"1\" }, { \"b1\": \"\\\/$kbmPrefixFormatted$\\\/\", \"cmd\": 90.0, \"obsid\": \"Main\", \"pos\": 6.0, \"vis\": 1.0, \"ms\": 0.0, \"sel\": false, \"dis\": 0.0, \"xpan\": 0.0, \"b0\": \"kbmPrefixLower\" }, { \"b53\": \"\", \"b5\": \"on\", \"b13\": \"==\", \"v14\": 0.0, \"b36\": \"\", \"b38\": \"\", \"v10\": 0.0, \"b32\": \"\", \"b19\": \"==\", \"b57\": \"\", \"b59\": \"\", \"b17\": \"\", \"b1\": \"==\", \"v18\": 0.0, \"v16\": 0.0, \"b34\": \"==\", \"b7\": \"==\", \"b11\": \"yes\", \"b9\": \"kbmPrefixLower\", \"b51\": \"\", \"b15\": \"\", \"b3\": \"kbmPrefixLower\", \"b55\": \"==\", \"v12\": 0.0, \"cmd\": 7.0, \"b30\": \"\", \"b43\": \"==\", \"v21\": 0.0, \"v1\": 2.0, \"b26\": \"\", \"b28\": \"==\", \"obsid\": \"Main\", \"b22\": \"==\", \"pos\": 7.0, \"v5\": 2.0, \"b47\": \"\", \"b49\": \"==\", \"v3\": 0.0, \"vis\": 1.0, \"b24\": \"\", \"ms\": 0.0, \"b41\": \"\", \"sel\": false, \"b45\": \"\", \"v9\": 0.0, \"dis\": 0.0, \"xpan\": 75.0, \"b20\": \"\", \"v7\": 0.0, \"b33\": \"\", \"v11\": 0.0, \"b16\": \"==\", \"b0\": \"kbmPrefixLower\", \"b58\": \"==\", \"b56\": \"\", \"b18\": \"\", \"b4\": \"==\", \"b12\": \"\", \"b52\": \"==\", \"b39\": \"\", \"b37\": \"==\", \"v15\": 0.0, \"b54\": \"\", \"b14\": \"\", \"b2\": \"true\", \"b31\": \"==\", \"v13\": 0.0, \"b35\": \"\", \"v17\": 0.0, \"v19\": 0.0, \"b50\": \"\", \"b8\": \"1\", \"b6\": \"kbmPrefixLower\", \"b10\": \"==\", \"b23\": \"\", \"v4\": 2.0, \"b48\": \"\", \"b46\": \"==\", \"v20\": 0.0, \"b42\": \"\", \"b29\": \"\", \"v0\": 2.0, \"b27\": \"\", \"b44\": \"\", \"b21\": \"\", \"v6\": 2.0, \"v8\": 0.0, \"v2\": 4.0, \"b25\": \"==\", \"b40\": \"==\", \"v22\": 0.0 }, { \"b1\": \"core\", \"b3\": \"keyBOTmedic: \", \"cmd\": 126.0, \"obsid\": \"Main\", \"pos\": 8.0, \"vis\": 1.0, \"ms\": 0.0, \"sel\": false, \"dis\": 0.0, \"xpan\": 0.0, \"b0\": \"kbmSettings.ini\", \"b2\": \"prefix\" }, { \"b1\": \"\\\/$kbmChannelName$\\\/\", \"cmd\": 148.0, \"obsid\": \"Main\", \"pos\": 9.0, \"vis\": 1.0, \"ms\": 0.0, \"sel\": false, \"dis\": 0.0, \"xpan\": 0.0, \"b0\": \"\\\/$kbmPrefix$\\\/ use of \\\"SAMMI:\\\" prefix set to On\" }, { \"b1\": \"core\", \"b3\": \"\", \"cmd\": 126.0, \"obsid\": \"Main\", \"pos\": 10.0, \"vis\": 1.0, \"ms\": 0.0, \"sel\": false, \"dis\": 0.0, \"xpan\": 0.0, \"b0\": \"kbmSettings.ini\", \"b2\": \"prefix\" }, { \"b1\": \"\\\/$kbmChannelName$\\\/\", \"cmd\": 148.0, \"obsid\": \"Main\", \"pos\": 11.0, \"vis\": 1.0, \"ms\": 0.0, \"sel\": false, \"dis\": 0.0, \"xpan\": 0.0, \"b0\": \"\\\/$kbmPrefix$\\\/use of \\\"SAMMI:\\\" prefix set to Off\" } ], \"press_type\": 0.0, \"x\": 0.20000000000000001110223024625157, \"border\": 2.0, \"image\": \"\", \"triggers\": [ { \"sub\": 0.0, \"user_name\": \"\", \"case_sensitive\": 0.0, \"founder\": 0.0, \"message\": \"!prefix *\", \"moderator\": 0.0, \"group_id\": \"\", \"vip\": 0.0, \"button_id\": \"ID6\", \"broadcaster\": 1.0, \"trg\": 0.0, \"allow_empty_wildcard\": 0.0 } ], \"group_id\": \"\", \"overlappable\": 0.0, \"init_variable\": \"\", \"deck\": 1.0, \"width\": 0.10000000000000000555111512312578, \"button_id\": \"ID6\", \"button_duration\": 0.0, \"y\": 0.10000000000000000555111512312578, \"switch_deck\": \"\", \"height\": 0.10000000000000000555111512312578, \"release_list\": [ ], \"functions\": 81.0, \"stretch\": 0.0 }, { \"color\": 12632256.0, \"persistent\": 1.0, \"text\": \"update INI\", \"release_duration\": 0.0, \"queueable\": 0.0, \"command_list\": [ { \"cmd\": 6.0, \"obsid\": \"Main\", \"pos\": 0.0, \"vis\": 1.0, \"ms\": 0.0, \"sel\": 0.0, \"dis\": 0.0, \"xpan\": 0.0, \"b0\": \"Automaticly adds needed keys to ini when they do not exsist\", \"v0\": 0.0 }, { \"b1\": \"core\", \"b3\": \"kbmIniChannelNameExsists\", \"cmd\": 131.0, \"obsid\": \"Main\", \"pos\": 1.0, \"vis\": 1.0, \"ms\": 0.0, \"sel\": 0.0, \"dis\": 0.0, \"xpan\": 0.0, \"b0\": \"kbmSettings.ini\", \"b2\": \"channelName\" }, { \"b1\": \"core\", \"b3\": \"kbmIniPrefixExsists\", \"cmd\": 131.0, \"obsid\": \"Main\", \"pos\": 2.0, \"vis\": 1.0, \"ms\": 0.0, \"sel\": 0.0, \"dis\": 0.0, \"xpan\": 0.0, \"b0\": \"kbmSettings.ini\", \"b2\": \"prefix\" }, { \"b53\": \"\", \"b5\": \"false\", \"b13\": \"==\", \"v14\": 0.0, \"b36\": \"\", \"b38\": \"\", \"v10\": 0.0, \"b32\": \"\", \"b19\": \"==\", \"b57\": \"\", \"b59\": \"\", \"b17\": \"\", \"b1\": \"==\", \"v18\": 0.0, \"v16\": 0.0, \"b34\": \"==\", \"b7\": \"==\", \"b11\": \"\", \"b9\": \"\", \"b51\": \"\", \"b15\": \"\", \"b3\": \"kbmIniPrefixExsists\", \"b55\": \"==\", \"v12\": 0.0, \"cmd\": 7.0, \"b30\": \"\", \"b43\": \"==\", \"v21\": 0.0, \"v1\": 0.0, \"b26\": \"\", \"b28\": \"==\", \"obsid\": \"Main\", \"b22\": \"==\", \"pos\": 3.0, \"v5\": 1.0, \"b47\": \"\", \"b49\": \"==\", \"v3\": 0.0, \"vis\": 1.0, \"b24\": \"\", \"ms\": 0.0, \"b41\": \"\", \"sel\": 0.0, \"b45\": \"\", \"v9\": 0.0, \"dis\": 0.0, \"xpan\": 0.0, \"b20\": \"\", \"v7\": 0.0, \"b33\": \"\", \"v11\": 0.0, \"b16\": \"==\", \"b0\": \"kbmIniChannelNameExsists\", \"b58\": \"==\", \"b56\": \"\", \"b18\": \"\", \"b4\": \"==\", \"b12\": \"\", \"b52\": \"==\", \"b39\": \"\", \"b37\": \"==\", \"v15\": 0.0, \"b54\": \"\", \"b14\": \"\", \"b2\": \"false\", \"b31\": \"==\", \"v13\": 0.0, \"b35\": \"\", \"v17\": 0.0, \"v19\": 0.0, \"b50\": \"\", \"b8\": \"false\", \"b6\": \"\", \"b10\": \"==\", \"b23\": \"\", \"v4\": 1.0, \"b48\": \"\", \"b46\": \"==\", \"v20\": 0.0, \"b42\": \"\", \"b29\": \"\", \"v0\": 1.0, \"b27\": \"\", \"b44\": \"\", \"b21\": \"\", \"v6\": 0.0, \"v8\": 0.0, \"v2\": 1.0, \"b25\": \"==\", \"b40\": \"==\", \"v22\": 0.0 }, { \"b1\": \"core\", \"b3\": \"\", \"cmd\": 126.0, \"obsid\": \"Main\", \"pos\": 4.0, \"vis\": 1.0, \"ms\": 0.0, \"sel\": 0.0, \"dis\": 0.0, \"xpan\": 0.0, \"b0\": \"kbmSettings.ini\", \"b2\": \"channelName\" }, { \"b53\": \"\", \"b5\": \"\", \"b13\": \"==\", \"v14\": 0.0, \"b36\": \"\", \"b38\": \"\", \"v10\": 0.0, \"b32\": \"\", \"b19\": \"==\", \"b57\": \"\", \"b59\": \"\", \"b17\": \"\", \"b1\": \"==\", \"v18\": 0.0, \"v16\": 0.0, \"b34\": \"==\", \"b7\": \"==\", \"b11\": \"\", \"b9\": \"\", \"b51\": \"\", \"b15\": \"\", \"b3\": \"\", \"b55\": \"==\", \"v12\": 0.0, \"cmd\": 7.0, \"b30\": \"\", \"b43\": \"==\", \"v21\": 0.0, \"v1\": 0.0, \"b26\": \"\", \"b28\": \"==\", \"obsid\": \"Main\", \"b22\": \"==\", \"pos\": 5.0, \"v5\": 0.0, \"b47\": \"\", \"b49\": \"==\", \"v3\": 0.0, \"vis\": 1.0, \"b24\": \"\", \"ms\": 0.0, \"b41\": \"\", \"sel\": 0.0, \"b45\": \"\", \"v9\": 0.0, \"dis\": 0.0, \"xpan\": 0.0, \"b20\": \"\", \"v7\": 0.0, \"b33\": \"\", \"v11\": 0.0, \"b16\": \"==\", \"b0\": \"kbmIniPrefixExsists\", \"b58\": \"==\", \"b56\": \"\", \"b18\": \"\", \"b4\": \"==\", \"b12\": \"\", \"b52\": \"==\", \"b39\": \"\", \"b37\": \"==\", \"v15\": 0.0, \"b54\": \"\", \"b14\": \"\", \"b2\": \"false\", \"b31\": \"==\", \"v13\": 0.0, \"b35\": \"\", \"v17\": 0.0, \"v19\": 0.0, \"b50\": \"\", \"b8\": \"\", \"b6\": \"\", \"b10\": \"==\", \"b23\": \"\", \"v4\": 0.0, \"b48\": \"\", \"b46\": \"==\", \"v20\": 0.0, \"b42\": \"\", \"b29\": \"\", \"v0\": 1.0, \"b27\": \"\", \"b44\": \"\", \"b21\": \"\", \"v6\": 0.0, \"v8\": 0.0, \"v2\": 1.0, \"b25\": \"==\", \"b40\": \"==\", \"v22\": 0.0 }, { \"b1\": \"core\", \"b3\": \"keyBOTmedic: \", \"cmd\": 126.0, \"obsid\": \"Main\", \"pos\": 6.0, \"vis\": 1.0, \"ms\": 0.0, \"sel\": 0.0, \"dis\": 0.0, \"xpan\": 0.0, \"b0\": \"kbmSettings.ini\", \"b2\": \"prefix\" } ], \"press_type\": 0.0, \"x\": 0.0, \"border\": 2.0, \"image\": \"\", \"triggers\": [ { \"group_id\": \"\", \"type\": \"SAMMI Startup\", \"button_id\": \"ID5\", \"trg\": 10.0 } ], \"group_id\": \"\", \"overlappable\": 0.0, \"init_variable\": \"\", \"deck\": 1.0, \"width\": 0.10000000000000000555111512312578, \"button_id\": \"ID5\", \"button_duration\": 0.0, \"y\": 0.29999999999999998889776975374843, \"switch_deck\": \"\", \"height\": 0.10000000000000000555111512312578, \"release_list\": [ ], \"functions\": 81.0, \"stretch\": 0.0 }, { \"color\": 12632256.0, \"persistent\": 1.0, \"text\": \"!keybotmedic\", \"release_duration\": 0.0, \"queueable\": 0.0, \"command_list\": [ { \"cmd\": 6.0, \"obsid\": \"Main\", \"pos\": 0.0, \"vis\": 1.0, \"ms\": 0.0, \"sel\": 0.0, \"dis\": 0.0, \"xpan\": 0.0, \"b0\": \"pulls settings from ini for channel output and use of prefix\", \"v0\": 0.0 }, { \"b1\": \"core\", \"b3\": \"kbmChannelName\", \"cmd\": 127.0, \"obsid\": \"Main\", \"pos\": 1.0, \"vis\": 1.0, \"ms\": 0.0, \"sel\": 0.0, \"dis\": 0.0, \"xpan\": 0.0, \"b0\": \"kbmSettings.ini\", \"b2\": \"channelName\" }, { \"b1\": \"core\", \"b3\": \"kbmPrefix\", \"cmd\": 127.0, \"obsid\": \"Main\", \"pos\": 2.0, \"vis\": 1.0, \"ms\": 0.0, \"sel\": 0.0, \"dis\": 0.0, \"xpan\": 0.0, \"b0\": \"kbmSettings.ini\", \"b2\": \"prefix\" }, { \"cmd\": 6.0, \"obsid\": \"Main\", \"pos\": 3.0, \"vis\": 1.0, \"ms\": 0.0, \"sel\": 0.0, \"dis\": 0.0, \"xpan\": 0.0, \"b0\": \"Disclaimer written by me to display in your channel if people ask about the bot\", \"v0\": 0.0 }, { \"b1\": \"\\\/$kbmChannelName$\\\/\", \"cmd\": 148.0, \"obsid\": \"Main\", \"pos\": 4.0, \"vis\": 1.0, \"ms\": 0.0, \"sel\": 0.0, \"dis\": 0.0, \"xpan\": 0.0, \"b0\": \"\\\/$kbmPrefix$\\\/Message from KeyboardMedic: keybotmedic was created for my own personal use, its a combination of sammi decks. I am willing to share it but i do not offer any support. your free to use it and modify it but if you break it its on you ¯\\\\_(ツ)_\\\/¯\" } ], \"press_type\": 0.0, \"x\": 0.20000000000000001110223024625157, \"border\": 2.0, \"image\": \"\", \"triggers\": [ { \"sub\": 0.0, \"user_name\": \"\", \"case_sensitive\": 0.0, \"founder\": 0.0, \"message\": \"!keybotmedic\", \"moderator\": 0.0, \"group_id\": \"\", \"vip\": 0.0, \"button_id\": \"ID20\", \"broadcaster\": 0.0, \"trg\": 0.0, \"allow_empty_wildcard\": 0.0 } ], \"group_id\": \"\", \"overlappable\": 0.0, \"init_variable\": \"\", \"deck\": 1.0, \"width\": 0.10000000000000000555111512312578, \"button_id\": \"ID20\", \"button_duration\": 0.0, \"y\": 0.0, \"switch_deck\": \"\", \"height\": 0.10000000000000000555111512312578, \"release_list\": [ ], \"functions\": 81.0, \"stretch\": 0.0 }, { \"color\": 12632256.0, \"persistent\": 1.0, \"text\": \"!kbmversion\", \"release_duration\": 0.0, \"queueable\": 0.0, \"command_list\": [ { \"cmd\": 6.0, \"obsid\": \"Main\", \"pos\": 0.0, \"vis\": 1.0, \"ms\": 0.0, \"sel\": 0.0, \"dis\": 0.0, \"xpan\": 0.0, \"b0\": \"pulls settings from ini for channel output and use of prefix\", \"v0\": 0.0 }, { \"b1\": \"core\", \"b3\": \"kbmChannelName\", \"cmd\": 127.0, \"obsid\": \"Main\", \"pos\": 1.0, \"vis\": 1.0, \"ms\": 0.0, \"sel\": 0.0, \"dis\": 0.0, \"xpan\": 0.0, \"b0\": \"kbmSettings.ini\", \"b2\": \"channelName\" }, { \"b1\": \"core\", \"b3\": \"kbmPrefix\", \"cmd\": 127.0, \"obsid\": \"Main\", \"pos\": 2.0, \"vis\": 1.0, \"ms\": 0.0, \"sel\": 0.0, \"dis\": 0.0, \"xpan\": 0.0, \"b0\": \"kbmSettings.ini\", \"b2\": \"prefix\" }, { \"cmd\": 6.0, \"obsid\": \"Main\", \"pos\": 3.0, \"vis\": 1.0, \"ms\": 0.0, \"sel\": 0.0, \"dis\": 0.0, \"xpan\": 0.0, \"b0\": \"displays current version in chat\", \"v0\": 0.0 }, { \"b1\": \"\\\/$kbmChannelName$\\\/\", \"cmd\": 148.0, \"obsid\": \"Main\", \"pos\": 4.0, \"vis\": 1.0, \"ms\": 0.0, \"sel\": 0.0, \"dis\": 0.0, \"xpan\": 0.0, \"b0\": \"\\\/$kbmPrefix$\\\/ KBM core version: 69.0\" } ], \"press_type\": 0.0, \"x\": 0.10000000000000000555111512312578, \"border\": 2.0, \"image\": \"\", \"triggers\": [ { \"sub\": 0.0, \"user_name\": \"\", \"case_sensitive\": 0.0, \"founder\": 0.0, \"message\": \"!kbmversion\", \"moderator\": 1.0, \"group_id\": \"\", \"vip\": 0.0, \"button_id\": \"ID25\", \"broadcaster\": 0.0, \"trg\": 0.0, \"allow_empty_wildcard\": 0.0 } ], \"group_id\": \"\", \"overlappable\": 0.0, \"init_variable\": \"\", \"deck\": 1.0, \"width\": 0.10000000000000000555111512312578, \"button_id\": \"ID25\", \"button_duration\": 0.0, \"y\": 0.29999999999999998889776975374843, \"switch_deck\": \"\", \"height\": 0.10000000000000000555111512312578, \"release_list\": [ ], \"functions\": 81.0, \"stretch\": 0.0 }, { \"color\": 12632256.0, \"persistent\": true, \"text\": \"!roles\", \"release_duration\": 0.0, \"queueable\": false, \"command_list\": [ { \"b1\": \"core\", \"b3\": \"kbmChannelName\", \"cmd\": 127.0, \"obsid\": \"Main\", \"pos\": 0.0, \"vis\": 1.0, \"ms\": 0.0, \"sel\": false, \"dis\": 0.0, \"xpan\": 0.0, \"b0\": \"kbmSettings.ini\", \"b2\": \"channelName\" }, { \"b1\": \"core\", \"b3\": \"kbmPrefix\", \"cmd\": 127.0, \"obsid\": \"Main\", \"pos\": 1.0, \"vis\": 1.0, \"ms\": 0.0, \"sel\": false, \"dis\": 0.0, \"xpan\": 0.0, \"b0\": \"kbmSettings.ini\", \"b2\": \"prefix\" }, { \"b1\": \"\\\/$kbmChannelName$\\\/\", \"cmd\": 148.0, \"obsid\": \"Main\", \"pos\": 2.0, \"vis\": true, \"ms\": 0.0, \"sel\": false, \"dis\": false, \"xpan\": 0.0, \"b0\": \"\\\/$kbmPrefix$\\\/Roles can be selected here: https:\\\/\\\/dashboard.twitch.tv\\\/u\\\/\\\/$kbmChannelName$\\\/\\\/community\\\/roles\" } ], \"press_type\": 0.0, \"x\": 0.40000000000000002220446049250313, \"border\": 2.0, \"image\": \"\", \"triggers\": [ { \"sub\": false, \"user_name\": \"\", \"case_sensitive\": false, \"founder\": false, \"message\": \"!roles\", \"moderator\": true, \"group_id\": \"\", \"vip\": false, \"button_id\": \"ID36\", \"broadcaster\": false, \"trg\": 0.0, \"allow_empty_wildcard\": false } ], \"group_id\": \"\", \"overlappable\": false, \"init_variable\": \"\", \"deck\": 1.0, \"width\": 0.10000000000000000555111512312578, \"button_id\": \"ID36\", \"button_duration\": 0.0, \"y\": 0.0, \"switch_deck\": \"\", \"height\": 0.10000000000000000555111512312578, \"release_list\": [ ], \"functions\": 81, \"stretch\": false }, { \"color\": 12632256.0, \"persistent\": true, \"text\": \"!moderation\", \"release_duration\": 0.0, \"queueable\": false, \"command_list\": [ { \"b1\": \"core\", \"b3\": \"kbmChannelName\", \"cmd\": 127.0, \"obsid\": \"Main\", \"pos\": 0.0, \"vis\": 1.0, \"ms\": 0.0, \"sel\": false, \"dis\": 0.0, \"xpan\": 0.0, \"b0\": \"kbmSettings.ini\", \"b2\": \"channelName\" }, { \"b1\": \"core\", \"b3\": \"kbmPrefix\", \"cmd\": 127.0, \"obsid\": \"Main\", \"pos\": 1.0, \"vis\": 1.0, \"ms\": 0.0, \"sel\": false, \"dis\": 0.0, \"xpan\": 0.0, \"b0\": \"kbmSettings.ini\", \"b2\": \"prefix\" }, { \"b1\": \"\\\/$kbmChannelName$\\\/\", \"cmd\": 148.0, \"obsid\": \"Main\", \"pos\": 2.0, \"vis\": true, \"ms\": 0.0, \"sel\": false, \"dis\": false, \"xpan\": 0.0, \"b0\": \"\\\/$kbmPrefix$\\\/Moderation settings are here: https:\\\/\\\/dashboard.twitch.tv\\\/u\\\/\\\/$kbmChannelName$\\\/\\\/settings\\\/moderation\" } ], \"press_type\": 0.0, \"x\": 0.40000000000000002220446049250313, \"border\": 2.0, \"image\": \"\", \"triggers\": [ { \"sub\": false, \"user_name\": \"\", \"case_sensitive\": false, \"founder\": false, \"message\": \"!moderation\", \"moderator\": true, \"group_id\": \"\", \"vip\": false, \"button_id\": \"ID37\", \"broadcaster\": false, \"trg\": 0.0, \"allow_empty_wildcard\": false } ], \"group_id\": \"\", \"overlappable\": false, \"init_variable\": \"\", \"deck\": 1.0, \"width\": 0.10000000000000000555111512312578, \"button_id\": \"ID37\", \"button_duration\": 0.0, \"y\": 0.10000000000000000555111512312578, \"switch_deck\": \"\", \"height\": 0.10000000000000000555111512312578, \"release_list\": [ ], \"functions\": 81.0, \"stretch\": false } ], \"deck_name\": \"KBM Sammi core\", \"grid_x\": 10.0, \"stretch\": 0.0 }", "unique_id": "20221110062830968484619", "deck_verification_code": "3b00f34e50aee6ac85eec6c5a5b20166c7d126aa", "include_image": { } }